carsdata/__init__.py
carsdata/analyze/__init__.py
carsdata/analyze/analyzer.py
carsdata/analyze/factory.py
carsdata/analyze/reducer.py
carsdata/analyze/autoencoders/__init__.py
carsdata/analyze/autoencoders/factory.py
carsdata/analyze/autoencoders/normalizer.py
carsdata/analyze/autoencoders/unmixing.py
carsdata/analyze/mcr/__init__.py
carsdata/analyze/mcr/constraints.py
carsdata/analyze/mcr/regressors.py
carsdata/utils/__init__.py
carsdata/utils/chan_sandberg_vese.py
carsdata/utils/color_maps.py
carsdata/utils/colors.py
carsdata/utils/common.py
carsdata/utils/data.py
carsdata/utils/errors.py
carsdata/utils/files.py
carsdata/utils/math.py
carsdata/utils/metrics.py
carsdata/utils/plot.py
carsdata/utils/simplisma.py
carsdata/utils/types.py
carsdata/utils/torch/__init__.py
carsdata/utils/torch/common.py
carsdata/utils/torch/datasets.py
carsdata/utils/torch/losses.py
carsdata/utils/torch/metrics.py
carsdata/utils/torch/optimizers.py
tests/__init__.py
tests/utils/__init__.py
tests/utils/fixtures.py
tests/utils/test_data.py
tests/utils/test_files.py
carsdata-0.1.dist-info/LICENSE
carsdata-0.1.dist-info/METADATA
carsdata-0.1.dist-info/WHEEL
carsdata-0.1.dist-info/top_level.txt
carsdata-0.1.dist-info/RECORD
