Metadata-Version: 2.1
Name: carsdata
Version: 0.1
Summary: Package to apply MCR-ALS on CARS images
Home-page: https://gitlab.xlim.fr/datacart/cars-data
Author: D. Boildieu
Author-email: damien.boildieu@xlim.fr
License: UNKNOWN
Platform: UNKNOWN
Classifier: Programming Language :: Python :: 3
Classifier: License :: OSI Approved :: MIT License
Classifier: Operating System :: OS Independent
Classifier: Intended Audience :: End Users/Desktop
Classifier: Intended Audience :: Developers
Requires-Python: >=3.8
License-File: LICENSE
Requires-Dist: numpy
Requires-Dist: pymcr
Requires-Dist: matplotlib
Provides-Extra: test
Requires-Dist: pytest ; extra == 'test'
Provides-Extra: torch
Requires-Dist: pytorch ; extra == 'torch'
